nssh/__init__.py
nssh/decorators.py
nssh/exceptions.py
nssh/helper.py
nssh/netmiko_compatability.py
nssh/result.py
nssh/channel/__init__.py
nssh/channel/channel.py
nssh/driver/__init__.py
nssh/driver/driver.py
nssh/driver/network_driver.py
nssh/driver/community/__init__.py
nssh/driver/core/__init__.py
nssh/driver/core/arista_eos/__init__.py
nssh/driver/core/arista_eos/driver.py
nssh/driver/core/cisco_iosxe/__init__.py
nssh/driver/core/cisco_iosxe/driver.py
nssh/driver/core/cisco_iosxr/__init__.py
nssh/driver/core/cisco_iosxr/driver.py
nssh/driver/core/cisco_iosxr/helper.py
nssh/driver/core/cisco_nxos/__init__.py
nssh/driver/core/cisco_nxos/driver.py
nssh/driver/core/juniper_junos/__init__.py
nssh/driver/core/juniper_junos/driver.py
nssh/driver/core/juniper_junos/helper.py
nssh/transport/__init__.py
nssh/transport/cssh2.py
nssh/transport/miko.py
nssh/transport/ptyprocess.py
nssh/transport/socket.py
nssh/transport/systemssh.py
nssh/transport/transport.py
tests/__init__.py
tests/functional/__init__.py
tests/functional/conftest.py
tests/functional/driver/__init__.py
tests/functional/driver/test_driver.py
tests/functional/driver/test_network_driver.py
tests/functional/driver/core/__init__.py
tests/functional/driver/core/cisco_iosxe/__init__.py
tests/functional/driver/core/cisco_iosxe/helper.py
tests/functional/driver/core/cisco_iosxe/test_driver.py
tests/unit/__init__.py
tests/unit/conftest.py
tests/unit/test_decorators.py
tests/unit/test_helper.py
tests/unit/test_netmiko_compatability.py
tests/unit/test_result.py
tests/unit/channel/__init__.py
tests/unit/channel/test_channel.py
tests/unit/driver/__init__.py
tests/unit/driver/ext_test_funcs.py
tests/unit/driver/test_driver.py
tests/unit/driver/test_network_driver.py
tests/unit/driver/core/__init__.py
tests/unit/driver/core/cisco_iosxe/__init__.py
tests/unit/driver/core/cisco_iosxe/test_driver.py
tests/unit/transport/__init__.py
tests/unit/transport/systemssh.py
tests/unit/transport/test_socket.py
nssh-2020.2.2.dist-info/LICENSE
nssh-2020.2.2.dist-info/METADATA
nssh-2020.2.2.dist-info/WHEEL
nssh-2020.2.2.dist-info/top_level.txt
nssh-2020.2.2.dist-info/RECORD
